CHANGES.rst
CONTRIBUTORS.rst
MANIFEST.in
README.rst
setup.py
collective/__init__.py
collective.betterbrowser.egg-info/PKG-INFO
collective.betterbrowser.egg-info/SOURCES.txt
collective.betterbrowser.egg-info/dependency_links.txt
collective.betterbrowser.egg-info/entry_points.txt
collective.betterbrowser.egg-info/namespace_packages.txt
collective.betterbrowser.egg-info/not-zip-safe
collective.betterbrowser.egg-info/requires.txt
collective.betterbrowser.egg-info/top_level.txt
collective/betterbrowser/__init__.py
collective/betterbrowser/browser.py
docs/LICENSE.txt