Metadata-Version: 1.1
Name: collective.betterbrowser
Version: 0.1
Summary: Inspect the contents of your plone.testing browser instance in a real browser (like Firefox), and more.
Home-page: https://github.com/collective/collective.betterbrowser
Author: Denis Krienbuehl
Author-email: denis.krienbuehl@gmail.com
License: MIT
Keywords: mechanize browser testing plone
Platform: UNKNOWN
Classifier: Framework :: Plone
Classifier: Framework :: Plone :: 4.3
Classifier: Intended Audience :: Developers
Classifier: Programming Language :: Python
Classifier: Topic :: Software Development :: Libraries :: Python Modules
